[
	{
		"route" : "/",
		"controller" : "sendClient"
	},

	{
		"route" : "/user/create",
		"controller" : "userCreate"
	},
	{
		"route" : "/user/edit",
		"controller" : "userEdit"
	},
	{
		"route" : "/user/remove",
		"controller" : "userRemove"
	},
	{
		"route" : "/user/read",
		"controller" : "userRead"
	},

	{
		"route" : "/task/create",
		"controller" : "taskCreate"
	},
	{
		"route" : "/task/edit",
		"controller" : "taskEdit"
	},
	{
		"route" : "/task/remove",
		"controller" : "taskRemove"
	},
	{
		"route" : "/task/read",
		"controller" : "taskRead"
	},

	{
		"route" : "/historyLog/create",
		"controller" : "historyLogCreate"
	},
	{
		"route" : "/historyLog/edit",
		"controller" : "historyLogEdit"
	},
	{
		"route" : "/historyLog/remove",
		"controller" : "historyLogRemove"
	},
	{
		"route" : "/historyLog/read",
		"controller" : "historyLogRead"
	}
]
